darepy/__init__.py
darepy/__main__.py
darepy/calibration.py
darepy/correction.py
darepy/integration.py
darepy/normalization.py
darepy/post_processing.py
darepy/prepare_input.py
darepy/transmission.py
darepy/utils.py
darepy/actions/__init__.py
darepy/actions/bsc.py
darepy/actions/init.py
darepy/actions/list.py
darepy/actions/merge.py
darepy/actions/radint.py
darepy/actions/rename.py
darepy/config/__init__.py
darepy/config/base.py
darepy/config/cfg.py
darepy/config/experiment.py
darepy/config/instruments.py
darepy/config/reduction.py
darepy/data/flat_field_SANS-I.txt
darepy/data/flat_field_SANS-LLB.txt
darepy/plotting/__init__.py
darepy/plotting/integration.py
darepy/plotting/pattern2D.py
darepy_sans-0.1.0.dist-info/METADATA
darepy_sans-0.1.0.dist-info/WHEEL
darepy_sans-0.1.0.dist-info/entry_points.txt
darepy_sans-0.1.0.dist-info/top_level.txt
darepy_sans-0.1.0.dist-info/RECORD
