Metadata-Version: 2.4
Name: darepy_sans
Version: 0.1.0
Summary: DarePy-SANS data reduction pipline
Author: Viviane Lutz-Bueno - Paul Scherrer Institut
Author-email: viviane.lutz-Bueno@psi.ch
License: MIT
Classifier: Programming Language :: Python :: 3
Classifier: License :: OSI Approved :: MIT License
Classifier: Operating System :: OS Independent
Classifier: Topic :: Scientific/Engineering
Classifier: Development Status :: 3 - Alpha
Requires-Python: >=3.8
Requires-Dist: numpy
Requires-Dist: h5py
Requires-Dist: matplotlib
Requires-Dist: pyFAI
Requires-Dist: tabulate
Requires-Dist: backports.strenum; python_version < "3.11"
Requires-Dist: ruamel.yaml
